{
    "routeId": "63",
    "routeName": "Yung Yat House (Yu Tung Road) > Caribbean Coast",
    "timetables": [
        {
            "days": "Monday to Friday",
            "timetable": [
                {
                    "time": "3 - 5",
                    "note": "07:35 - 08:15"
                },
                {
                    "time": "Headway (minutes)",
                    "note": "From Yu Tung Road"
                }
            ]
        },
        {
            "days": " ",
            "timetable": [
                {
                    "time": "No Service On Sat, Sun & Public Holidays",
                    "note": ""
                },
                {
                    "time": "No Service On School Holidays",
                    "note": ""
                }
            ]
        },
        {
            "days": " ",
            "timetable": [
                {
                    "time": "No Service On Sat, Sun & Public Holidays",
                    "note": ""
                },
                {
                    "time": "No Service On School Holidays",
                    "note": ""
                }
            ]
        }
    ],
    "notes": []
}